QuickGraphLib/__init__.py
QuickGraphLib/_QuickGraphLib.pyd
QuickGraphLib/_QuickGraphLib.pyi
QuickGraphLib/_version.py
QuickGraphLib/AntialiasingContainer.qml
QuickGraphLib/Axis.qml
QuickGraphLib/bindings/Bindings.hpp
QuickGraphLib/bindings/Bindings.xml
QuickGraphLib/bindings/CMakeLists.txt
QuickGraphLib/bindings/glue/DataTypes.cpp
QuickGraphLib/bindings/pyigen.py
QuickGraphLib/bindings/ShibokenHelpers.cpp
QuickGraphLib/bindings/ShibokenHelpers.hpp
QuickGraphLib/CMakeLists.txt
QuickGraphLib/ColorMaps.cpp
QuickGraphLib/ColorMaps.hpp
QuickGraphLib/consts.py
QuickGraphLib/contours.py
QuickGraphLib/DataTypes.cpp
QuickGraphLib/DataTypes.hpp
QuickGraphLib/doc/AxesGridLayout.drawio
QuickGraphLib/doc/AxesGridLayout.svg
QuickGraphLib/doc/export.qdoc
QuickGraphLib/doc/graphitems.qdoc
QuickGraphLib/doc/graphstructure.qdoc
QuickGraphLib/doc/index.qdoc
QuickGraphLib/doc/interaction.qdoc
QuickGraphLib/doc/module-cpp.qdoc
QuickGraphLib/doc/module.qdoc
QuickGraphLib/doc/prefabs.qdoc
QuickGraphLib/doc/python_helpers.qdoc
QuickGraphLib/Global.hpp
QuickGraphLib/GraphArea.qml
QuickGraphLib/GraphItems/AxHLine.qml
QuickGraphLib/GraphItems/AxHSpan.qml
QuickGraphLib/GraphItems/AxVLine.qml
QuickGraphLib/GraphItems/AxVSpan.qml
QuickGraphLib/GraphItems/BasicLegend.qml
QuickGraphLib/GraphItems/BasicLegendItem.qml
QuickGraphLib/GraphItems/CMakeLists.txt
QuickGraphLib/GraphItems/ColorMesh.qml
QuickGraphLib/GraphItems/Contour.qml
QuickGraphLib/GraphItems/GraphItemDragHandler.qml
QuickGraphLib/GraphItems/Grid.qml
QuickGraphLib/GraphItems/helpers/GridHelper.cpp
QuickGraphLib/GraphItems/helpers/GridHelper.hpp
QuickGraphLib/GraphItems/helpers/HistogramHelper.cpp
QuickGraphLib/GraphItems/helpers/HistogramHelper.hpp
QuickGraphLib/GraphItems/Histogram.qml
QuickGraphLib/GraphItems/Line.qml
QuickGraphLib/GraphItems/Marker.qml
QuickGraphLib/GraphItems/qmldir
QuickGraphLib/GraphItems/QuickGraphLibGraphItems.dll
QuickGraphLib/GraphItems/QuickGraphLibGraphItems.qmltypes
QuickGraphLib/helpers/AxisHelper.cpp
quickgraphlib-0.1.0a16.dist-info/METADATA
quickgraphlib-0.1.0a16.dist-info/WHEEL
quickgraphlib-0.1.0a16.dist-info/licenses/LICENCE
quickgraphlib-0.1.0a16.dist-info/RECORD
