Metadata-Version: 2.2
Name: QuickGraphLib
Version: 0.1.0a16
Summary: A scientific graphing library for QtQuick
Author-Email: Matthew Joyce <matthew.joyce@refeyn.com>
License: MIT License
Classifier: Development Status :: 3 - Alpha
Classifier: Environment :: X11 Applications :: Qt
Classifier: Intended Audience :: Science/Research
Classifier: License :: OSI Approved :: MIT License
Classifier: Operating System :: OS Independent
Classifier: Programming Language :: Python
Classifier: Topic :: Multimedia :: Graphics :: Presentation
Classifier: Topic :: Scientific/Engineering :: Visualization
Classifier: Topic :: Software Development :: User Interfaces
Classifier: Typing :: Typed
Project-URL: Homepage, https://github.com/refeyn/QuickGraphLib
Project-URL: Issues, https://github.com/refeyn/QuickGraphLib/issues
Project-URL: Documentation, https://refeyn.github.io/QuickGraphLib
Project-URL: Source, https://github.com/refeyn/QuickGraphLib
Requires-Python: >=3.9
Requires-Dist: PySide6==6.10.0
Requires-Dist: contourpy
Requires-Dist: numpy
Provides-Extra: analyse
Requires-Dist: ruff; extra == "analyse"
Requires-Dist: mypy; extra == "analyse"
Requires-Dist: pre-commit; extra == "analyse"
Requires-Dist: lxml; extra == "analyse"
Requires-Dist: gersemi; extra == "analyse"
Requires-Dist: pytest; extra == "analyse"
Requires-Dist: pytest-cov; extra == "analyse"
Requires-Dist: scikit-build-core; extra == "analyse"
Requires-Dist: shiboken6_generator==6.10.0; extra == "analyse"
Requires-Dist: setuptools_scm; extra == "analyse"
